quicktype_ts/__init__.py
quicktype_ts/main.py
quicktype_ts-0.1.1.dist-info/METADATA
quicktype_ts-0.1.1.dist-info/WHEEL
quicktype_ts-0.1.1.dist-info/top_level.txt
quicktype_ts-0.1.1.dist-info/RECORD
