Metadata-Version: 2.1
Name: quicktype-ts
Version: 0.1.1
Summary: Generate typescript types from pydantic models (or JSON schemas) using Quicktype
Author-email: Marcel Claramunt <marcel@moveread.com>
Project-URL: repo, https://github.com/moveread/codegen.git
Requires-Python: >=3.10
Requires-Dist: pydantic
